crypto_contract_value-0.0.2.dist-info/METADATA
crypto_contract_value-0.0.2.dist-info/WHEEL
crypto_contract_value-0.0.2.dist-info/top_level.txt
crypto_contract_value-0.0.2.dist-info/RECORD
crypto_contract_value-0.0.2.dist-info/LICENSE
crypto_contract_value.libs/libkeyutils-dfe70bd6.so.1.5
crypto_contract_value.libs/libkrb5-fc820a1d.so.3.3
crypto_contract_value.libs/libz-745e0a09.so.1.2.7
crypto_contract_value.libs/libkrb5support-04204f6a.so.0.1
crypto_contract_value.libs/libselinux-0922c95c.so.1
crypto_contract_value.libs/libcrypto-45dd1549.so.1.0.2k
crypto_contract_value.libs/libgssapi_krb5-497db0c6.so.2.2
crypto_contract_value.libs/libcom_err-2abe824b.so.2.1
crypto_contract_value.libs/libssl-419c949b.so.1.0.2k
crypto_contract_value.libs/libpcre-9513aab5.so.1.2.0
crypto_contract_value.libs/libk5crypto-b1f99d5c.so.3.1
crypto_contract_value/_lowlevel__lib.so
crypto_contract_value/_lowlevel__ffi.py
crypto_contract_value/__init__.py
crypto_contract_value/_lowlevel.py
