Metadata-Version: 2.1
Name: crypto-contract-value
Version: 0.0.2
Summary: Get the unit value of a crypto contract
Home-page: https://github.com/soulmachine/crypto-contract-value-py
Author: soulmachine
License: UNKNOWN
Keywords: blockchain,cryptocurrency,trading
Platform: UNKNOWN
Classifier: Programming Language :: Python :: 3.6
Classifier: License :: OSI Approved :: Apache Software License
Classifier: Topic :: Software Development :: Libraries :: Python Modules
Requires-Python: >=3.6
License-File: LICENSE
Requires-Dist: milksnake
